NEMO_group_email/__init__.py
NEMO_group_email/urls.py
NEMO_group_email/templates/NEMO_group_email/email_broadcast.html
NEMO_group_email/tests/__init__.py
NEMO_group_email/tests/test_settings.py
NEMO_group_email/tests/views/__init__.py
NEMO_group_email/tests/views/email/__init__.py
NEMO_group_email/tests/views/email/test_unit.py
NEMO_group_email/views/__init__.py
NEMO_group_email/views/email.py
NEMO_group_email-2.0.0.dist-info/LICENSE
NEMO_group_email-2.0.0.dist-info/METADATA
NEMO_group_email-2.0.0.dist-info/WHEEL
NEMO_group_email-2.0.0.dist-info/top_level.txt
NEMO_group_email-2.0.0.dist-info/RECORD
