Metadata-Version: 2.1
Name: NEMO-group-email
Version: 2.0.0
Summary: Install Group email plugin for NEMO
Home-page: https://gitlab.com/nemo-community/prometheus-computing/nemo-group-email
Author: Prometheus Computing LLC
Author-email: nemo@prometheuscomputing.com
License: MIT
Keywords: NEMO
Classifier: Development Status :: 4 - Beta
Classifier: Intended Audience :: Developers
Classifier: License :: OSI Approved :: MIT License
Classifier: Programming Language :: Python :: 3.7
Requires-Python: >=3.7
License-File: LICENSE
Requires-Dist: NEMO (>=4.3.0)
Requires-Dist: NEMO-user-details (>=1.0.0)
Requires-Dist: django (<4.0,>=3.2)
